[
   {
      "model" : "cartograms.cartogram",
      "pk" : 1,
      "fields" : {
         "json_filename" : "texas.json",
         "cartogram_id" : "48",
         "name" : "Texas",
         "status" : true
      }
   },
   {
      "pk" : 1,
      "model" : "cartograms.cartogramentity",
      "fields" : {
         "cartogram" : 1,
         "status" : true,
         "entity_id" : "113",
         "name" : "Dallas"
      }
   },
   {
      "fields" : {
         "cartogram" : 1,
         "status" : true,
         "entity_id" : "227",
         "name" : "Howard"
      },
      "pk" : 2,
      "model" : "cartograms.cartogramentity"
   },
   {
      "pk" : 3,
      "model" : "cartograms.cartogramentity",
      "fields" : {
         "name" : "Foard",
         "status" : true,
         "entity_id" : "155",
         "cartogram" : 1
      }
   },
   {
      "pk" : 4,
      "model" : "cartograms.cartogramentity",
      "fields" : {
         "cartogram" : 1,
         "status" : true,
         "entity_id" : "153",
         "name" : "Floyd"
      }
   },
   {
      "fields" : {
         "entity_id" : "043",
         "status" : true,
         "cartogram" : 1,
         "name" : "Brewster"
      },
      "model" : "cartograms.cartogramentity",
      "pk" : 5
   },
   {
      "fields" : {
         "name" : "Franklin",
         "status" : true,
         "entity_id" : "159",
         "cartogram" : 1
      },
      "pk" : 6,
      "model" : "cartograms.cartogramentity"
   },
   {
      "fields" : {
         "status" : true,
         "entity_id" : "231",
         "cartogram" : 1,
         "name" : "Hunt"
      },
      "pk" : 7,
      "model" : "cartograms.cartogramentity"
   },
   {
      "pk" : 8,
      "model" : "cartograms.cartogramentity",
      "fields" : {
         "name" : "Newton",
         "cartogram" : 1,
         "status" : true,
         "entity_id" : "351"
      }
   },
   {
      "model" : "cartograms.cartogramentity",
      "pk" : 9,
      "fields" : {
         "name" : "Starr",
         "cartogram" : 1,
         "entity_id" : "427",
         "status" : true
      }
   },
   {
      "model" : "cartograms.cartogramentity",
      "pk" : 10,
      "fields" : {
         "name" : "Kinney",
         "cartogram" : 1,
         "status" : true,
         "entity_id" : "271"
      }
   },
   {
      "fields" : {
         "cartogram" : 1,
         "status" : true,
         "entity_id" : "087",
         "name" : "Collingsworth"
      },
      "model" : "cartograms.cartogramentity",
      "pk" : 11
   },
   {
      "fields" : {
         "name" : "Tom Green",
         "cartogram" : 1,
         "status" : true,
         "entity_id" : "451"
      },
      "model" : "cartograms.cartogramentity",
      "pk" : 12
   },
   {
      "model" : "cartograms.cartogramentity",
      "pk" : 13,
      "fields" : {
         "cartogram" : 1,
         "entity_id" : "083",
         "status" : true,
         "name" : "Coleman"
      }
   },
   {
      "pk" : 14,
      "model" : "cartograms.cartogramentity",
      "fields" : {
         "entity_id" : "039",
         "status" : true,
         "cartogram" : 1,
         "name" : "Brazoria"
      }
   },
   {
      "fields" : {
         "cartogram" : 1,
         "entity_id" : "289",
         "status" : true,
         "name" : "Leon"
      },
      "pk" : 15,
      "model" : "cartograms.cartogramentity"
   },
   {
      "model" : "cartograms.cartogramentity",
      "pk" : 16,
      "fields" : {
         "name" : "Duval",
         "status" : true,
         "entity_id" : "131",
         "cartogram" : 1
      }
   },
   {
      "fields" : {
         "cartogram" : 1,
         "status" : true,
         "entity_id" : "279",
         "name" : "Lamb"
      },
      "pk" : 17,
      "model" : "cartograms.cartogramentity"
   },
   {
      "fields" : {
         "status" : true,
         "entity_id" : "343",
         "cartogram" : 1,
         "name" : "Morris"
      },
      "pk" : 18,
      "model" : "cartograms.cartogramentity"
   },
   {
      "fields" : {
         "name" : "Smith",
         "entity_id" : "423",
         "status" : true,
         "cartogram" : 1
      },
      "model" : "cartograms.cartogramentity",
      "pk" : 19
   },
   {
      "pk" : 20,
      "model" : "cartograms.cartogramentity",
      "fields" : {
         "entity_id" : "239",
         "status" : true,
         "cartogram" : 1,
         "name" : "Jackson"
      }
   },
   {
      "fields" : {
         "name" : "Medina",
         "status" : true,
         "entity_id" : "325",
         "cartogram" : 1
      },
      "pk" : 21,
      "model" : "cartograms.cartogramentity"
   },
   {
      "fields" : {
         "cartogram" : 1,
         "status" : true,
         "entity_id" : "483",
         "name" : "Wheeler"
      },
      "pk" : 22,
      "model" : "cartograms.cartogramentity"
   },
   {
      "model" : "cartograms.cartogramentity",
      "pk" : 23,
      "fields" : {
         "status" : true,
         "entity_id" : "111",
         "cartogram" : 1,
         "name" : "Dallam"
      }
   },
   {
      "pk" : 24,
      "model" : "cartograms.cartogramentity",
      "fields" : {
         "name" : "Callahan",
         "entity_id" : "059",
         "status" : true,
         "cartogram" : 1
      }
   },
   {
      "pk" : 25,
      "model" : "cartograms.cartogramentity",
      "fields" : {
         "cartogram" : 1,
         "status" : true,
         "entity_id" : "277",
         "name" : "Lamar"
      }
   },
   {
      "model" : "cartograms.cartogramentity",
      "pk" : 26,
      "fields" : {
         "name" : "Coryell",
         "entity_id" : "099",
         "status" : true,
         "cartogram" : 1
      }
   },
   {
      "fields" : {
         "cartogram" : 1,
         "status" : true,
         "entity_id" : "165",
         "name" : "Gaines"
      },
      "pk" : 27,
      "model" : "cartograms.cartogramentity"
   },
   {
      "fields" : {
         "name" : "Kendall",
         "cartogram" : 1,
         "entity_id" : "259",
         "status" : true
      },
      "pk" : 28,
      "model" : "cartograms.cartogramentity"
   },
   {
      "fields" : {
         "name" : "Nacogdoches",
         "cartogram" : 1,
         "entity_id" : "347",
         "status" : true
      },
      "pk" : 29,
      "model" : "cartograms.cartogramentity"
   },
   {
      "fields" : {
         "name" : "Milam",
         "cartogram" : 1,
         "status" : true,
         "entity_id" : "331"
      },
      "model" : "cartograms.cartogramentity",
      "pk" : 30
   },
   {
      "fields" : {
         "cartogram" : 1,
         "entity_id" : "209",
         "status" : true,
         "name" : "Hays"
      },
      "model" : "cartograms.cartogramentity",
      "pk" : 31
   },
   {
      "fields" : {
         "cartogram" : 1,
         "entity_id" : "489",
         "status" : true,
         "name" : "Willacy"
      },
      "model" : "cartograms.cartogramentity",
      "pk" : 32
   },
   {
      "model" : "cartograms.cartogramentity",
      "pk" : 33,
      "fields" : {
         "name" : "Johnson",
         "cartogram" : 1,
         "status" : true,
         "entity_id" : "251"
      }
   },
   {
      "fields" : {
         "name" : "Reagan",
         "status" : true,
         "entity_id" : "383",
         "cartogram" : 1
      },
      "pk" : 34,
      "model" : "cartograms.cartogramentity"
   },
   {
      "model" : "cartograms.cartogramentity",
      "pk" : 35,
      "fields" : {
         "cartogram" : 1,
         "entity_id" : "479",
         "status" : true,
         "name" : "Webb"
      }
   },
   {
      "fields" : {
         "name" : "Shackelford",
         "entity_id" : "417",
         "status" : true,
         "cartogram" : 1
      },
      "model" : "cartograms.cartogramentity",
      "pk" : 36
   },
   {
      "fields" : {
         "name" : "Bowie",
         "status" : true,
         "entity_id" : "037",
         "cartogram" : 1
      },
      "model" : "cartograms.cartogramentity",
      "pk" : 37
   },
   {
      "model" : "cartograms.cartogramentity",
      "pk" : 38,
      "fields" : {
         "cartogram" : 1,
         "entity_id" : "415",
         "status" : true,
         "name" : "Scurry"
      }
   },
   {
      "fields" : {
         "entity_id" : "261",
         "status" : true,
         "cartogram" : 1,
         "name" : "Kenedy"
      },
      "model" : "cartograms.cartogramentity",
      "pk" : 39
   },
   {
      "fields" : {
         "cartogram" : 1,
         "status" : true,
         "entity_id" : "425",
         "name" : "Somervell"
      },
      "pk" : 40,
      "model" : "cartograms.cartogramentity"
   },
   {
      "fields" : {
         "cartogram" : 1,
         "status" : true,
         "entity_id" : "359",
         "name" : "Oldham"
      },
      "pk" : 41,
      "model" : "cartograms.cartogramentity"
   },
   {
      "model" : "cartograms.cartogramentity",
      "pk" : 42,
      "fields" : {
         "cartogram" : 1,
         "entity_id" : "441",
         "status" : true,
         "name" : "Taylor"
      }
   },
   {
      "fields" : {
         "cartogram" : 1,
         "status" : true,
         "entity_id" : "269",
         "name" : "King"
      },
      "pk" : 43,
      "model" : "cartograms.cartogramentity"
   },
   {
      "fields" : {
         "name" : "Borden",
         "status" : true,
         "entity_id" : "033",
         "cartogram" : 1
      },
      "model" : "cartograms.cartogramentity",
      "pk" : 44
   },
   {
      "fields" : {
         "cartogram" : 1,
         "entity_id" : "471",
         "status" : true,
         "name" : "Walker"
      },
      "model" : "cartograms.cartogramentity",
      "pk" : 45
   },
   {
      "fields" : {
         "name" : "Stephens",
         "status" : true,
         "entity_id" : "429",
         "cartogram" : 1
      },
      "model" : "cartograms.cartogramentity",
      "pk" : 46
   },
   {
      "model" : "cartograms.cartogramentity",
      "pk" : 47,
      "fields" : {
         "entity_id" : "117",
         "status" : true,
         "cartogram" : 1,
         "name" : "Deaf Smith"
      }
   },
   {
      "pk" : 48,
      "model" : "cartograms.cartogramentity",
      "fields" : {
         "name" : "Roberts",
         "cartogram" : 1,
         "status" : true,
         "entity_id" : "393"
      }
   },
   {
      "fields" : {
         "name" : "Tyler",
         "cartogram" : 1,
         "entity_id" : "457",
         "status" : true
      },
      "model" : "cartograms.cartogramentity",
      "pk" : 49
   },
   {
      "fields" : {
         "name" : "Val Verde",
         "entity_id" : "465",
         "status" : true,
         "cartogram" : 1
      },
      "pk" : 50,
      "model" : "cartograms.cartogramentity"
   },
   {
      "fields" : {
         "cartogram" : 1,
         "entity_id" : "049",
         "status" : true,
         "name" : "Brown"
      },
      "pk" : 51,
      "model" : "cartograms.cartogramentity"
   },
   {
      "fields" : {
         "name" : "Parker",
         "entity_id" : "367",
         "status" : true,
         "cartogram" : 1
      },
      "model" : "cartograms.cartogramentity",
      "pk" : 52
   },
   {
      "model" : "cartograms.cartogramentity",
      "pk" : 53,
      "fields" : {
         "name" : "Harris",
         "cartogram" : 1,
         "status" : true,
         "entity_id" : "201"
      }
   },
   {
      "model" : "cartograms.cartogramentity",
      "pk" : 54,
      "fields" : {
         "name" : "Zapata",
         "status" : true,
         "entity_id" : "505",
         "cartogram" : 1
      }
   },
   {
      "model" : "cartograms.cartogramentity",
      "pk" : 55,
      "fields" : {
         "cartogram" : 1,
         "status" : true,
         "entity_id" : "387",
         "name" : "Red River"
      }
   },
   {
      "fields" : {
         "name" : "Karnes",
         "status" : true,
         "entity_id" : "255",
         "cartogram" : 1
      },
      "pk" : 56,
      "model" : "cartograms.cartogramentity"
   },
   {
      "fields" : {
         "name" : "Palo Pinto",
         "status" : true,
         "entity_id" : "363",
         "cartogram" : 1
      },
      "pk" : 57,
      "model" : "cartograms.cartogramentity"
   },
   {
      "pk" : 58,
      "model" : "cartograms.cartogramentity",
      "fields" : {
         "name" : "Glasscock",
         "cartogram" : 1,
         "entity_id" : "173",
         "status" : true
      }
   },
   {
      "fields" : {
         "cartogram" : 1,
         "status" : true,
         "entity_id" : "419",
         "name" : "Shelby"
      },
      "model" : "cartograms.cartogramentity",
      "pk" : 59
   },
   {
      "fields" : {
         "entity_id" : "499",
         "status" : true,
         "cartogram" : 1,
         "name" : "Wood"
      },
      "model" : "cartograms.cartogramentity",
      "pk" : 60
   },
   {
      "fields" : {
         "name" : "Crosby",
         "entity_id" : "107",
         "status" : true,
         "cartogram" : 1
      },
      "pk" : 61,
      "model" : "cartograms.cartogramentity"
   },
   {
      "pk" : 62,
      "model" : "cartograms.cartogramentity",
      "fields" : {
         "status" : true,
         "entity_id" : "391",
         "cartogram" : 1,
         "name" : "Refugio"
      }
   },
   {
      "fields" : {
         "cartogram" : 1,
         "entity_id" : "053",
         "status" : true,
         "name" : "Burnet"
      },
      "pk" : 63,
      "model" : "cartograms.cartogramentity"
   },
   {
      "fields" : {
         "name" : "Sterling",
         "cartogram" : 1,
         "entity_id" : "431",
         "status" : true
      },
      "model" : "cartograms.cartogramentity",
      "pk" : 64
   },
   {
      "pk" : 65,
      "model" : "cartograms.cartogramentity",
      "fields" : {
         "cartogram" : 1,
         "status" : true,
         "entity_id" : "339",
         "name" : "Montgomery"
      }
   },
   {
      "model" : "cartograms.cartogramentity",
      "pk" : 66,
      "fields" : {
         "status" : true,
         "entity_id" : "405",
         "cartogram" : 1,
         "name" : "San Augustine"
      }
   },
   {
      "fields" : {
         "name" : "Rains",
         "cartogram" : 1,
         "status" : true,
         "entity_id" : "379"
      },
      "pk" : 67,
      "model" : "cartograms.cartogramentity"
   },
   {
      "model" : "cartograms.cartogramentity",
      "pk" : 68,
      "fields" : {
         "name" : "Nueces",
         "cartogram" : 1,
         "status" : true,
         "entity_id" : "355"
      }
   },
   {
      "model" : "cartograms.cartogramentity",
      "pk" : 69,
      "fields" : {
         "name" : "Jack",
         "cartogram" : 1,
         "entity_id" : "237",
         "status" : true
      }
   },
   {
      "pk" : 70,
      "model" : "cartograms.cartogramentity",
      "fields" : {
         "name" : "Swisher",
         "status" : true,
         "entity_id" : "437",
         "cartogram" : 1
      }
   },
   {
      "fields" : {
         "name" : "Camp",
         "cartogram" : 1,
         "status" : true,
         "entity_id" : "063"
      },
      "model" : "cartograms.cartogramentity",
      "pk" : 71
   },
   {
      "model" : "cartograms.cartogramentity",
      "pk" : 72,
      "fields" : {
         "name" : "Brazos",
         "status" : true,
         "entity_id" : "041",
         "cartogram" : 1
      }
   },
   {
      "fields" : {
         "name" : "Orange",
         "cartogram" : 1,
         "entity_id" : "361",
         "status" : true
      },
      "model" : "cartograms.cartogramentity",
      "pk" : 73
   },
   {
      "fields" : {
         "cartogram" : 1,
         "status" : true,
         "entity_id" : "089",
         "name" : "Colorado"
      },
      "model" : "cartograms.cartogramentity",
      "pk" : 74
   },
   {
      "model" : "cartograms.cartogramentity",
      "pk" : 75,
      "fields" : {
         "cartogram" : 1,
         "status" : true,
         "entity_id" : "371",
         "name" : "Pecos"
      }
   },
   {
      "model" : "cartograms.cartogramentity",
      "pk" : 76,
      "fields" : {
         "status" : true,
         "entity_id" : "079",
         "cartogram" : 1,
         "name" : "Cochran"
      }
   },
   {
      "model" : "cartograms.cartogramentity",
      "pk" : 77,
      "fields" : {
         "name" : "Parmer",
         "entity_id" : "369",
         "status" : true,
         "cartogram" : 1
      }
   },
   {
      "pk" : 78,
      "model" : "cartograms.cartogramentity",
      "fields" : {
         "name" : "Freestone",
         "cartogram" : 1,
         "entity_id" : "161",
         "status" : true
      }
   },
   {
      "fields" : {
         "cartogram" : 1,
         "entity_id" : "495",
         "status" : true,
         "name" : "Winkler"
      },
      "model" : "cartograms.cartogramentity",
      "pk" : 79
   },
   {
      "model" : "cartograms.cartogramentity",
      "pk" : 80,
      "fields" : {
         "name" : "Wichita",
         "status" : true,
         "entity_id" : "485",
         "cartogram" : 1
      }
   },
   {
      "fields" : {
         "cartogram" : 1,
         "status" : true,
         "entity_id" : "179",
         "name" : "Gray"
      },
      "pk" : 81,
      "model" : "cartograms.cartogramentity"
   },
   {
      "fields" : {
         "cartogram" : 1,
         "status" : true,
         "entity_id" : "413",
         "name" : "Schleicher"
      },
      "pk" : 82,
      "model" : "cartograms.cartogramentity"
   },
   {
      "fields" : {
         "name" : "Hardeman",
         "cartogram" : 1,
         "entity_id" : "197",
         "status" : true
      },
      "pk" : 83,
      "model" : "cartograms.cartogramentity"
   },
   {
      "model" : "cartograms.cartogramentity",
      "pk" : 84,
      "fields" : {
         "entity_id" : "453",
         "status" : true,
         "cartogram" : 1,
         "name" : "Travis"
      }
   },
   {
      "pk" : 85,
      "model" : "cartograms.cartogramentity",
      "fields" : {
         "name" : "Gillespie",
         "cartogram" : 1,
         "status" : true,
         "entity_id" : "171"
      }
   },
   {
      "fields" : {
         "cartogram" : 1,
         "status" : true,
         "entity_id" : "501",
         "name" : "Yoakum"
      },
      "pk" : 86,
      "model" : "cartograms.cartogramentity"
   },
   {
      "fields" : {
         "status" : true,
         "entity_id" : "149",
         "cartogram" : 1,
         "name" : "Fayette"
      },
      "pk" : 87,
      "model" : "cartograms.cartogramentity"
   },
   {
      "model" : "cartograms.cartogramentity",
      "pk" : 88,
      "fields" : {
         "name" : "Uvalde",
         "entity_id" : "463",
         "status" : true,
         "cartogram" : 1
      }
   },
   {
      "pk" : 89,
      "model" : "cartograms.cartogramentity",
      "fields" : {
         "cartogram" : 1,
         "status" : true,
         "entity_id" : "185",
         "name" : "Grimes"
      }
   },
   {
      "pk" : 90,
      "model" : "cartograms.cartogramentity",
      "fields" : {
         "name" : "Van Zandt",
         "entity_id" : "467",
         "status" : true,
         "cartogram" : 1
      }
   },
   {
      "pk" : 91,
      "model" : "cartograms.cartogramentity",
      "fields" : {
         "name" : "Throckmorton",
         "status" : true,
         "entity_id" : "447",
         "cartogram" : 1
      }
   },
   {
      "model" : "cartograms.cartogramentity",
      "pk" : 92,
      "fields" : {
         "name" : "Falls",
         "entity_id" : "145",
         "status" : true,
         "cartogram" : 1
      }
   },
   {
      "fields" : {
         "name" : "Grayson",
         "entity_id" : "181",
         "status" : true,
         "cartogram" : 1
      },
      "model" : "cartograms.cartogramentity",
      "pk" : 93
   },
   {
      "pk" : 94,
      "model" : "cartograms.cartogramentity",
      "fields" : {
         "name" : "Ellis",
         "status" : true,
         "entity_id" : "139",
         "cartogram" : 1
      }
   },
   {
      "fields" : {
         "name" : "Hall",
         "entity_id" : "191",
         "status" : true,
         "cartogram" : 1
      },
      "model" : "cartograms.cartogramentity",
      "pk" : 95
   },
   {
      "model" : "cartograms.cartogramentity",
      "pk" : 96,
      "fields" : {
         "cartogram" : 1,
         "entity_id" : "125",
         "status" : true,
         "name" : "Dickens"
      }
   },
   {
      "pk" : 97,
      "model" : "cartograms.cartogramentity",
      "fields" : {
         "cartogram" : 1,
         "status" : true,
         "entity_id" : "455",
         "name" : "Trinity"
      }
   },
   {
      "model" : "cartograms.cartogramentity",
      "pk" : 98,
      "fields" : {
         "name" : "Reeves",
         "cartogram" : 1,
         "status" : true,
         "entity_id" : "389"
      }
   },
   {
      "fields" : {
         "entity_id" : "315",
         "status" : true,
         "cartogram" : 1,
         "name" : "Marion"
      },
      "model" : "cartograms.cartogramentity",
      "pk" : 99
   },
   {
      "fields" : {
         "name" : "Terrell",
         "cartogram" : 1,
         "entity_id" : "443",
         "status" : true
      },
      "pk" : 100,
      "model" : "cartograms.cartogramentity"
   },
   {
      "model" : "cartograms.cartogramentity",
      "pk" : 101,
      "fields" : {
         "status" : true,
         "entity_id" : "305",
         "cartogram" : 1,
         "name" : "Lynn"
      }
   },
   {
      "fields" : {
         "name" : "La Salle",
         "entity_id" : "283",
         "status" : true,
         "cartogram" : 1
      },
      "model" : "cartograms.cartogramentity",
      "pk" : 102
   },
   {
      "pk" : 103,
      "model" : "cartograms.cartogramentity",
      "fields" : {
         "entity_id" : "241",
         "status" : true,
         "cartogram" : 1,
         "name" : "Jasper"
      }
   },
   {
      "fields" : {
         "name" : "Jones",
         "cartogram" : 1,
         "status" : true,
         "entity_id" : "253"
      },
      "pk" : 104,
      "model" : "cartograms.cartogramentity"
   },
   {
      "model" : "cartograms.cartogramentity",
      "pk" : 105,
      "fields" : {
         "name" : "Castro",
         "cartogram" : 1,
         "status" : true,
         "entity_id" : "069"
      }
   },
   {
      "fields" : {
         "name" : "Victoria",
         "entity_id" : "469",
         "status" : true,
         "cartogram" : 1
      },
      "pk" : 106,
      "model" : "cartograms.cartogramentity"
   },
   {
      "model" : "cartograms.cartogramentity",
      "pk" : 107,
      "fields" : {
         "status" : true,
         "entity_id" : "273",
         "cartogram" : 1,
         "name" : "Kleberg"
      }
   },
   {
      "model" : "cartograms.cartogramentity",
      "pk" : 108,
      "fields" : {
         "cartogram" : 1,
         "status" : true,
         "entity_id" : "045",
         "name" : "Briscoe"
      }
   },
   {
      "pk" : 109,
      "model" : "cartograms.cartogramentity",
      "fields" : {
         "name" : "Clay",
         "cartogram" : 1,
         "entity_id" : "077",
         "status" : true
      }
   },
   {
      "pk" : 110,
      "model" : "cartograms.cartogramentity",
      "fields" : {
         "name" : "Matagorda",
         "status" : true,
         "entity_id" : "321",
         "cartogram" : 1
      }
   },
   {
      "fields" : {
         "cartogram" : 1,
         "entity_id" : "047",
         "status" : true,
         "name" : "Brooks"
      },
      "pk" : 111,
      "model" : "cartograms.cartogramentity"
   },
   {
      "pk" : 112,
      "model" : "cartograms.cartogramentity",
      "fields" : {
         "name" : "Runnels",
         "status" : true,
         "entity_id" : "399",
         "cartogram" : 1
      }
   },
   {
      "model" : "cartograms.cartogramentity",
      "pk" : 113,
      "fields" : {
         "entity_id" : "065",
         "status" : true,
         "cartogram" : 1,
         "name" : "Carson"
      }
   },
   {
      "pk" : 114,
      "model" : "cartograms.cartogramentity",
      "fields" : {
         "name" : "Liberty",
         "cartogram" : 1,
         "entity_id" : "291",
         "status" : true
      }
   },
   {
      "fields" : {
         "cartogram" : 1,
         "entity_id" : "287",
         "status" : true,
         "name" : "Lee"
      },
      "pk" : 115,
      "model" : "cartograms.cartogramentity"
   },
   {
      "fields" : {
         "cartogram" : 1,
         "entity_id" : "189",
         "status" : true,
         "name" : "Hale"
      },
      "model" : "cartograms.cartogramentity",
      "pk" : 116
   },
   {
      "fields" : {
         "name" : "Bexar",
         "cartogram" : 1,
         "status" : true,
         "entity_id" : "029"
      },
      "model" : "cartograms.cartogramentity",
      "pk" : 117
   },
   {
      "fields" : {
         "name" : "Garza",
         "status" : true,
         "entity_id" : "169",
         "cartogram" : 1
      },
      "model" : "cartograms.cartogramentity",
      "pk" : 118
   },
   {
      "pk" : 119,
      "model" : "cartograms.cartogramentity",
      "fields" : {
         "cartogram" : 1,
         "status" : true,
         "entity_id" : "337",
         "name" : "Montague"
      }
   },
   {
      "model" : "cartograms.cartogramentity",
      "pk" : 120,
      "fields" : {
         "cartogram" : 1,
         "status" : true,
         "entity_id" : "461",
         "name" : "Upton"
      }
   },
   {
      "model" : "cartograms.cartogramentity",
      "pk" : 121,
      "fields" : {
         "status" : true,
         "entity_id" : "193",
         "cartogram" : 1,
         "name" : "Hamilton"
      }
   },
   {
      "pk" : 122,
      "model" : "cartograms.cartogramentity",
      "fields" : {
         "entity_id" : "151",
         "status" : true,
         "cartogram" : 1,
         "name" : "Fisher"
      }
   },
   {
      "fields" : {
         "status" : true,
         "entity_id" : "115",
         "cartogram" : 1,
         "name" : "Dawson"
      },
      "model" : "cartograms.cartogramentity",
      "pk" : 123
   },
   {
      "fields" : {
         "name" : "Dimmit",
         "entity_id" : "127",
         "status" : true,
         "cartogram" : 1
      },
      "model" : "cartograms.cartogramentity",
      "pk" : 124
   },
   {
      "model" : "cartograms.cartogramentity",
      "pk" : 125,
      "fields" : {
         "name" : "Limestone",
         "cartogram" : 1,
         "entity_id" : "293",
         "status" : true
      }
   },
   {
      "model" : "cartograms.cartogramentity",
      "pk" : 126,
      "fields" : {
         "cartogram" : 1,
         "status" : true,
         "entity_id" : "233",
         "name" : "Hutchinson"
      }
   },
   {
      "pk" : 127,
      "model" : "cartograms.cartogramentity",
      "fields" : {
         "entity_id" : "299",
         "status" : true,
         "cartogram" : 1,
         "name" : "Llano"
      }
   },
   {
      "model" : "cartograms.cartogramentity",
      "pk" : 128,
      "fields" : {
         "entity_id" : "377",
         "status" : true,
         "cartogram" : 1,
         "name" : "Presidio"
      }
   },
   {
      "fields" : {
         "name" : "Eastland",
         "status" : true,
         "entity_id" : "133",
         "cartogram" : 1
      },
      "model" : "cartograms.cartogramentity",
      "pk" : 129
   },
   {
      "model" : "cartograms.cartogramentity",
      "pk" : 130,
      "fields" : {
         "name" : "Sabine",
         "status" : true,
         "entity_id" : "403",
         "cartogram" : 1
      }
   },
   {
      "model" : "cartograms.cartogramentity",
      "pk" : 131,
      "fields" : {
         "name" : "Wharton",
         "cartogram" : 1,
         "status" : true,
         "entity_id" : "481"
      }
   },
   {
      "fields" : {
         "name" : "Rusk",
         "status" : true,
         "entity_id" : "401",
         "cartogram" : 1
      },
      "pk" : 132,
      "model" : "cartograms.cartogramentity"
   },
   {
      "fields" : {
         "entity_id" : "439",
         "status" : true,
         "cartogram" : 1,
         "name" : "Tarrant"
      },
      "pk" : 133,
      "model" : "cartograms.cartogramentity"
   },
   {
      "pk" : 134,
      "model" : "cartograms.cartogramentity",
      "fields" : {
         "name" : "Lavaca",
         "status" : true,
         "entity_id" : "285",
         "cartogram" : 1
      }
   },
   {
      "model" : "cartograms.cartogramentity",
      "pk" : 135,
      "fields" : {
         "cartogram" : 1,
         "status" : true,
         "entity_id" : "075",
         "name" : "Childress"
      }
   },
   {
      "fields" : {
         "name" : "Hidalgo",
         "cartogram" : 1,
         "status" : true,
         "entity_id" : "215"
      },
      "pk" : 136,
      "model" : "cartograms.cartogramentity"
   },
   {
      "model" : "cartograms.cartogramentity",
      "pk" : 137,
      "fields" : {
         "name" : "Kaufman",
         "cartogram" : 1,
         "entity_id" : "257",
         "status" : true
      }
   },
   {
      "fields" : {
         "name" : "Moore",
         "cartogram" : 1,
         "status" : true,
         "entity_id" : "341"
      },
      "model" : "cartograms.cartogramentity",
      "pk" : 138
   },
   {
      "model" : "cartograms.cartogramentity",
      "pk" : 139,
      "fields" : {
         "name" : "Menard",
         "cartogram" : 1,
         "status" : true,
         "entity_id" : "327"
      }
   },
   {
      "pk" : 140,
      "model" : "cartograms.cartogramentity",
      "fields" : {
         "name" : "Edwards",
         "cartogram" : 1,
         "status" : true,
         "entity_id" : "137"
      }
   },
   {
      "fields" : {
         "cartogram" : 1,
         "entity_id" : "409",
         "status" : true,
         "name" : "San Patricio"
      },
      "pk" : 141,
      "model" : "cartograms.cartogramentity"
   },
   {
      "fields" : {
         "name" : "Terry",
         "cartogram" : 1,
         "entity_id" : "445",
         "status" : true
      },
      "pk" : 142,
      "model" : "cartograms.cartogramentity"
   },
   {
      "pk" : 143,
      "model" : "cartograms.cartogramentity",
      "fields" : {
         "name" : "Crockett",
         "entity_id" : "105",
         "status" : true,
         "cartogram" : 1
      }
   },
   {
      "fields" : {
         "name" : "Houston",
         "cartogram" : 1,
         "status" : true,
         "entity_id" : "225"
      },
      "pk" : 144,
      "model" : "cartograms.cartogramentity"
   },
   {
      "fields" : {
         "status" : true,
         "entity_id" : "473",
         "cartogram" : 1,
         "name" : "Waller"
      },
      "model" : "cartograms.cartogramentity",
      "pk" : 145
   },
   {
      "fields" : {
         "name" : "Coke",
         "cartogram" : 1,
         "status" : true,
         "entity_id" : "081"
      },
      "pk" : 146,
      "model" : "cartograms.cartogramentity"
   },
   {
      "fields" : {
         "entity_id" : "475",
         "status" : true,
         "cartogram" : 1,
         "name" : "Ward"
      },
      "pk" : 147,
      "model" : "cartograms.cartogramentity"
   },
   {
      "pk" : 148,
      "model" : "cartograms.cartogramentity",
      "fields" : {
         "name" : "Titus",
         "cartogram" : 1,
         "entity_id" : "449",
         "status" : true
      }
   },
   {
      "model" : "cartograms.cartogramentity",
      "pk" : 149,
      "fields" : {
         "name" : "Lampasas",
         "cartogram" : 1,
         "status" : true,
         "entity_id" : "281"
      }
   },
   {
      "fields" : {
         "status" : true,
         "entity_id" : "207",
         "cartogram" : 1,
         "name" : "Haskell"
      },
      "pk" : 150,
      "model" : "cartograms.cartogramentity"
   },
   {
      "fields" : {
         "name" : "Martin",
         "status" : true,
         "entity_id" : "317",
         "cartogram" : 1
      },
      "pk" : 151,
      "model" : "cartograms.cartogramentity"
   },
   {
      "model" : "cartograms.cartogramentity",
      "pk" : 152,
      "fields" : {
         "name" : "Atascosa",
         "cartogram" : 1,
         "entity_id" : "013",
         "status" : true
      }
   },
   {
      "fields" : {
         "name" : "Hemphill",
         "status" : true,
         "entity_id" : "211",
         "cartogram" : 1
      },
      "pk" : 153,
      "model" : "cartograms.cartogramentity"
   },
   {
      "model" : "cartograms.cartogramentity",
      "pk" : 154,
      "fields" : {
         "name" : "Hartley",
         "entity_id" : "205",
         "status" : true,
         "cartogram" : 1
      }
   },
   {
      "pk" : 155,
      "model" : "cartograms.cartogramentity",
      "fields" : {
         "name" : "Young",
         "cartogram" : 1,
         "status" : true,
         "entity_id" : "503"
      }
   },
   {
      "pk" : 156,
      "model" : "cartograms.cartogramentity",
      "fields" : {
         "name" : "Burleson",
         "entity_id" : "051",
         "status" : true,
         "cartogram" : 1
      }
   },
   {
      "fields" : {
         "name" : "Hardin",
         "entity_id" : "199",
         "status" : true,
         "cartogram" : 1
      },
      "model" : "cartograms.cartogramentity",
      "pk" : 157
   },
   {
      "pk" : 158,
      "model" : "cartograms.cartogramentity",
      "fields" : {
         "name" : "Gonzales",
         "status" : true,
         "entity_id" : "177",
         "cartogram" : 1
      }
   },
   {
      "model" : "cartograms.cartogramentity",
      "pk" : 159,
      "fields" : {
         "entity_id" : "311",
         "status" : true,
         "cartogram" : 1,
         "name" : "McMullen"
      }
   },
   {
      "fields" : {
         "entity_id" : "143",
         "status" : true,
         "cartogram" : 1,
         "name" : "Erath"
      },
      "pk" : 160,
      "model" : "cartograms.cartogramentity"
   },
   {
      "model" : "cartograms.cartogramentity",
      "pk" : 161,
      "fields" : {
         "cartogram" : 1,
         "status" : true,
         "entity_id" : "167",
         "name" : "Galveston"
      }
   },
   {
      "fields" : {
         "name" : "Hopkins",
         "status" : true,
         "entity_id" : "223",
         "cartogram" : 1
      },
      "pk" : 162,
      "model" : "cartograms.cartogramentity"
   },
   {
      "pk" : 163,
      "model" : "cartograms.cartogramentity",
      "fields" : {
         "name" : "McLennan",
         "entity_id" : "309",
         "status" : true,
         "cartogram" : 1
      }
   },
   {
      "model" : "cartograms.cartogramentity",
      "pk" : 164,
      "fields" : {
         "name" : "Madison",
         "cartogram" : 1,
         "entity_id" : "313",
         "status" : true
      }
   },
   {
      "model" : "cartograms.cartogramentity",
      "pk" : 165,
      "fields" : {
         "name" : "McCulloch",
         "status" : true,
         "entity_id" : "307",
         "cartogram" : 1
      }
   },
   {
      "fields" : {
         "cartogram" : 1,
         "entity_id" : "129",
         "status" : true,
         "name" : "Donley"
      },
      "model" : "cartograms.cartogramentity",
      "pk" : 166
   },
   {
      "model" : "cartograms.cartogramentity",
      "pk" : 167,
      "fields" : {
         "name" : "Kent",
         "cartogram" : 1,
         "entity_id" : "263",
         "status" : true
      }
   },
   {
      "fields" : {
         "name" : "Real",
         "status" : true,
         "entity_id" : "385",
         "cartogram" : 1
      },
      "model" : "cartograms.cartogramentity",
      "pk" : 168
   },
   {
      "model" : "cartograms.cartogramentity",
      "pk" : 169,
      "fields" : {
         "cartogram" : 1,
         "status" : true,
         "entity_id" : "435",
         "name" : "Sutton"
      }
   },
   {
      "fields" : {
         "entity_id" : "329",
         "status" : true,
         "cartogram" : 1,
         "name" : "Midland"
      },
      "pk" : 170,
      "model" : "cartograms.cartogramentity"
   },
   {
      "model" : "cartograms.cartogramentity",
      "pk" : 171,
      "fields" : {
         "cartogram" : 1,
         "status" : true,
         "entity_id" : "229",
         "name" : "Hudspeth"
      }
   },
   {
      "model" : "cartograms.cartogramentity",
      "pk" : 172,
      "fields" : {
         "name" : "Zavala",
         "status" : true,
         "entity_id" : "507",
         "cartogram" : 1
      }
   },
   {
      "fields" : {
         "name" : "Harrison",
         "entity_id" : "203",
         "status" : true,
         "cartogram" : 1
      },
      "model" : "cartograms.cartogramentity",
      "pk" : 173
   },
   {
      "fields" : {
         "name" : "Comanche",
         "cartogram" : 1,
         "status" : true,
         "entity_id" : "093"
      },
      "pk" : 174,
      "model" : "cartograms.cartogramentity"
   },
   {
      "fields" : {
         "name" : "Mitchell",
         "cartogram" : 1,
         "entity_id" : "335",
         "status" : true
      },
      "model" : "cartograms.cartogramentity",
      "pk" : 175
   },
   {
      "fields" : {
         "cartogram" : 1,
         "status" : true,
         "entity_id" : "349",
         "name" : "Navarro"
      },
      "pk" : 176,
      "model" : "cartograms.cartogramentity"
   },
   {
      "pk" : 177,
      "model" : "cartograms.cartogramentity",
      "fields" : {
         "entity_id" : "103",
         "status" : true,
         "cartogram" : 1,
         "name" : "Crane"
      }
   },
   {
      "fields" : {
         "name" : "Lubbock",
         "entity_id" : "303",
         "status" : true,
         "cartogram" : 1
      },
      "model" : "cartograms.cartogramentity",
      "pk" : 178
   },
   {
      "fields" : {
         "cartogram" : 1,
         "entity_id" : "497",
         "status" : true,
         "name" : "Wise"
      },
      "model" : "cartograms.cartogramentity",
      "pk" : 179
   },
   {
      "model" : "cartograms.cartogramentity",
      "pk" : 180,
      "fields" : {
         "cartogram" : 1,
         "entity_id" : "477",
         "status" : true,
         "name" : "Washington"
      }
   },
   {
      "model" : "cartograms.cartogramentity",
      "pk" : 181,
      "fields" : {
         "name" : "Jeff Davis",
         "cartogram" : 1,
         "status" : true,
         "entity_id" : "243"
      }
   },
   {
      "fields" : {
         "status" : true,
         "entity_id" : "141",
         "cartogram" : 1,
         "name" : "El Paso"
      },
      "pk" : 182,
      "model" : "cartograms.cartogramentity"
   },
   {
      "fields" : {
         "name" : "Gregg",
         "cartogram" : 1,
         "status" : true,
         "entity_id" : "183"
      },
      "model" : "cartograms.cartogramentity",
      "pk" : 183
   },
   {
      "model" : "cartograms.cartogramentity",
      "pk" : 184,
      "fields" : {
         "name" : "Williamson",
         "cartogram" : 1,
         "status" : true,
         "entity_id" : "491"
      }
   },
   {
      "fields" : {
         "name" : "Lipscomb",
         "status" : true,
         "entity_id" : "295",
         "cartogram" : 1
      },
      "pk" : 185,
      "model" : "cartograms.cartogramentity"
   },
   {
      "fields" : {
         "name" : "Mason",
         "cartogram" : 1,
         "entity_id" : "319",
         "status" : true
      },
      "model" : "cartograms.cartogramentity",
      "pk" : 186
   },
   {
      "fields" : {
         "name" : "Henderson",
         "cartogram" : 1,
         "status" : true,
         "entity_id" : "213"
      },
      "pk" : 187,
      "model" : "cartograms.cartogramentity"
   },
   {
      "fields" : {
         "name" : "Hansford",
         "entity_id" : "195",
         "status" : true,
         "cartogram" : 1
      },
      "model" : "cartograms.cartogramentity",
      "pk" : 188
   },
   {
      "pk" : 189,
      "model" : "cartograms.cartogramentity",
      "fields" : {
         "cartogram" : 1,
         "entity_id" : "071",
         "status" : true,
         "name" : "Chambers"
      }
   },
   {
      "model" : "cartograms.cartogramentity",
      "pk" : 190,
      "fields" : {
         "status" : true,
         "entity_id" : "217",
         "cartogram" : 1,
         "name" : "Hill"
      }
   },
   {
      "fields" : {
         "entity_id" : "375",
         "status" : true,
         "cartogram" : 1,
         "name" : "Potter"
      },
      "model" : "cartograms.cartogramentity",
      "pk" : 191
   },
   {
      "model" : "cartograms.cartogramentity",
      "pk" : 192,
      "fields" : {
         "name" : "Jim Wells",
         "entity_id" : "249",
         "status" : true,
         "cartogram" : 1
      }
   },
   {
      "model" : "cartograms.cartogramentity",
      "pk" : 193,
      "fields" : {
         "name" : "Delta",
         "cartogram" : 1,
         "status" : true,
         "entity_id" : "119"
      }
   },
   {
      "model" : "cartograms.cartogramentity",
      "pk" : 194,
      "fields" : {
         "name" : "Stonewall",
         "cartogram" : 1,
         "status" : true,
         "entity_id" : "433"
      }
   },
   {
      "pk" : 195,
      "model" : "cartograms.cartogramentity",
      "fields" : {
         "cartogram" : 1,
         "status" : true,
         "entity_id" : "135",
         "name" : "Ector"
      }
   },
   {
      "fields" : {
         "status" : true,
         "entity_id" : "061",
         "cartogram" : 1,
         "name" : "Cameron"
      },
      "model" : "cartograms.cartogramentity",
      "pk" : 196
   },
   {
      "pk" : 197,
      "model" : "cartograms.cartogramentity",
      "fields" : {
         "cartogram" : 1,
         "entity_id" : "323",
         "status" : true,
         "name" : "Maverick"
      }
   },
   {
      "fields" : {
         "name" : "Collin",
         "cartogram" : 1,
         "status" : true,
         "entity_id" : "085"
      },
      "model" : "cartograms.cartogramentity",
      "pk" : 198
   },
   {
      "fields" : {
         "cartogram" : 1,
         "status" : true,
         "entity_id" : "023",
         "name" : "Baylor"
      },
      "pk" : 199,
      "model" : "cartograms.cartogramentity"
   },
   {
      "pk" : 200,
      "model" : "cartograms.cartogramentity",
      "fields" : {
         "cartogram" : 1,
         "status" : true,
         "entity_id" : "365",
         "name" : "Panola"
      }
   },
   {
      "fields" : {
         "entity_id" : "187",
         "status" : true,
         "cartogram" : 1,
         "name" : "Guadalupe"
      },
      "model" : "cartograms.cartogramentity",
      "pk" : 201
   },
   {
      "model" : "cartograms.cartogramentity",
      "pk" : 202,
      "fields" : {
         "name" : "Bastrop",
         "status" : true,
         "entity_id" : "021",
         "cartogram" : 1
      }
   },
   {
      "fields" : {
         "name" : "Austin",
         "status" : true,
         "entity_id" : "015",
         "cartogram" : 1
      },
      "model" : "cartograms.cartogramentity",
      "pk" : 203
   },
   {
      "pk" : 204,
      "model" : "cartograms.cartogramentity",
      "fields" : {
         "name" : "Andrews",
         "status" : true,
         "entity_id" : "003",
         "cartogram" : 1
      }
   },
   {
      "model" : "cartograms.cartogramentity",
      "pk" : 205,
      "fields" : {
         "name" : "Anderson",
         "cartogram" : 1,
         "entity_id" : "001",
         "status" : true
      }
   },
   {
      "fields" : {
         "name" : "Blanco",
         "entity_id" : "031",
         "status" : true,
         "cartogram" : 1
      },
      "pk" : 206,
      "model" : "cartograms.cartogramentity"
   },
   {
      "model" : "cartograms.cartogramentity",
      "pk" : 207,
      "fields" : {
         "name" : "DeWitt",
         "entity_id" : "123",
         "status" : true,
         "cartogram" : 1
      }
   },
   {
      "fields" : {
         "cartogram" : 1,
         "status" : true,
         "entity_id" : "019",
         "name" : "Bandera"
      },
      "pk" : 208,
      "model" : "cartograms.cartogramentity"
   },
   {
      "model" : "cartograms.cartogramentity",
      "pk" : 209,
      "fields" : {
         "name" : "Bell",
         "status" : true,
         "entity_id" : "027",
         "cartogram" : 1
      }
   },
   {
      "fields" : {
         "name" : "Aransas",
         "cartogram" : 1,
         "status" : true,
         "entity_id" : "007"
      },
      "model" : "cartograms.cartogramentity",
      "pk" : 210
   },
   {
      "fields" : {
         "name" : "Archer",
         "cartogram" : 1,
         "entity_id" : "009",
         "status" : true
      },
      "model" : "cartograms.cartogramentity",
      "pk" : 211
   },
   {
      "model" : "cartograms.cartogramentity",
      "pk" : 212,
      "fields" : {
         "name" : "Armstrong",
         "cartogram" : 1,
         "entity_id" : "011",
         "status" : true
      }
   },
   {
      "fields" : {
         "status" : true,
         "entity_id" : "025",
         "cartogram" : 1,
         "name" : "Bee"
      },
      "model" : "cartograms.cartogramentity",
      "pk" : 213
   },
   {
      "model" : "cartograms.cartogramentity",
      "pk" : 214,
      "fields" : {
         "name" : "Angelina",
         "status" : true,
         "entity_id" : "005",
         "cartogram" : 1
      }
   },
   {
      "pk" : 215,
      "model" : "cartograms.cartogramentity",
      "fields" : {
         "name" : "Bailey",
         "status" : true,
         "entity_id" : "017",
         "cartogram" : 1
      }
   },
   {
      "pk" : 216,
      "model" : "cartograms.cartogramentity",
      "fields" : {
         "name" : "Jefferson",
         "cartogram" : 1,
         "entity_id" : "245",
         "status" : true
      }
   },
   {
      "model" : "cartograms.cartogramentity",
      "pk" : 217,
      "fields" : {
         "name" : "Frio",
         "status" : true,
         "entity_id" : "163",
         "cartogram" : 1
      }
   },
   {
      "model" : "cartograms.cartogramentity",
      "pk" : 218,
      "fields" : {
         "entity_id" : "147",
         "status" : true,
         "cartogram" : 1,
         "name" : "Fannin"
      }
   },
   {
      "pk" : 219,
      "model" : "cartograms.cartogramentity",
      "fields" : {
         "name" : "Goliad",
         "status" : true,
         "entity_id" : "175",
         "cartogram" : 1
      }
   },
   {
      "model" : "cartograms.cartogramentity",
      "pk" : 220,
      "fields" : {
         "entity_id" : "301",
         "status" : true,
         "cartogram" : 1,
         "name" : "Loving"
      }
   },
   {
      "pk" : 221,
      "model" : "cartograms.cartogramentity",
      "fields" : {
         "entity_id" : "067",
         "status" : true,
         "cartogram" : 1,
         "name" : "Cass"
      }
   },
   {
      "fields" : {
         "cartogram" : 1,
         "status" : true,
         "entity_id" : "157",
         "name" : "Fort Bend"
      },
      "model" : "cartograms.cartogramentity",
      "pk" : 222
   },
   {
      "pk" : 223,
      "model" : "cartograms.cartogramentity",
      "fields" : {
         "cartogram" : 1,
         "entity_id" : "035",
         "status" : true,
         "name" : "Bosque"
      }
   },
   {
      "fields" : {
         "entity_id" : "219",
         "status" : true,
         "cartogram" : 1,
         "name" : "Hockley"
      },
      "pk" : 224,
      "model" : "cartograms.cartogramentity"
   },
   {
      "pk" : 225,
      "model" : "cartograms.cartogramentity",
      "fields" : {
         "name" : "San Saba",
         "status" : true,
         "entity_id" : "411",
         "cartogram" : 1
      }
   },
   {
      "fields" : {
         "name" : "Kerr",
         "cartogram" : 1,
         "status" : true,
         "entity_id" : "265"
      },
      "model" : "cartograms.cartogramentity",
      "pk" : 226
   },
   {
      "fields" : {
         "name" : "Mills",
         "entity_id" : "333",
         "status" : true,
         "cartogram" : 1
      },
      "model" : "cartograms.cartogramentity",
      "pk" : 227
   },
   {
      "fields" : {
         "name" : "Cooke",
         "cartogram" : 1,
         "entity_id" : "097",
         "status" : true
      },
      "model" : "cartograms.cartogramentity",
      "pk" : 228
   },
   {
      "model" : "cartograms.cartogramentity",
      "pk" : 229,
      "fields" : {
         "name" : "Wilbarger",
         "cartogram" : 1,
         "status" : true,
         "entity_id" : "487"
      }
   },
   {
      "fields" : {
         "name" : "Irion",
         "cartogram" : 1,
         "entity_id" : "235",
         "status" : true
      },
      "model" : "cartograms.cartogramentity",
      "pk" : 230
   },
   {
      "fields" : {
         "name" : "Caldwell",
         "entity_id" : "055",
         "status" : true,
         "cartogram" : 1
      },
      "pk" : 231,
      "model" : "cartograms.cartogramentity"
   },
   {
      "fields" : {
         "name" : "Jim Hogg",
         "status" : true,
         "entity_id" : "247",
         "cartogram" : 1
      },
      "model" : "cartograms.cartogramentity",
      "pk" : 232
   },
   {
      "pk" : 233,
      "model" : "cartograms.cartogramentity",
      "fields" : {
         "name" : "Culberson",
         "status" : true,
         "entity_id" : "109",
         "cartogram" : 1
      }
   },
   {
      "fields" : {
         "cartogram" : 1,
         "entity_id" : "459",
         "status" : true,
         "name" : "Upshur"
      },
      "model" : "cartograms.cartogramentity",
      "pk" : 234
   },
   {
      "fields" : {
         "name" : "Cherokee",
         "status" : true,
         "entity_id" : "073",
         "cartogram" : 1
      },
      "pk" : 235,
      "model" : "cartograms.cartogramentity"
   },
   {
      "model" : "cartograms.cartogramentity",
      "pk" : 236,
      "fields" : {
         "name" : "Denton",
         "status" : true,
         "entity_id" : "121",
         "cartogram" : 1
      }
   },
   {
      "model" : "cartograms.cartogramentity",
      "pk" : 237,
      "fields" : {
         "cartogram" : 1,
         "entity_id" : "095",
         "status" : true,
         "name" : "Concho"
      }
   },
   {
      "pk" : 238,
      "model" : "cartograms.cartogramentity",
      "fields" : {
         "name" : "Randall",
         "status" : true,
         "entity_id" : "381",
         "cartogram" : 1
      }
   },
   {
      "fields" : {
         "name" : "Kimble",
         "cartogram" : 1,
         "entity_id" : "267",
         "status" : true
      },
      "pk" : 239,
      "model" : "cartograms.cartogramentity"
   },
   {
      "fields" : {
         "name" : "Knox",
         "status" : true,
         "entity_id" : "275",
         "cartogram" : 1
      },
      "model" : "cartograms.cartogramentity",
      "pk" : 240
   },
   {
      "fields" : {
         "name" : "Polk",
         "cartogram" : 1,
         "entity_id" : "373",
         "status" : true
      },
      "pk" : 241,
      "model" : "cartograms.cartogramentity"
   },
   {
      "model" : "cartograms.cartogramentity",
      "pk" : 242,
      "fields" : {
         "entity_id" : "221",
         "status" : true,
         "cartogram" : 1,
         "name" : "Hood"
      }
   },
   {
      "fields" : {
         "name" : "San Jacinto",
         "entity_id" : "407",
         "status" : true,
         "cartogram" : 1
      },
      "pk" : 243,
      "model" : "cartograms.cartogramentity"
   },
   {
      "model" : "cartograms.cartogramentity",
      "pk" : 244,
      "fields" : {
         "entity_id" : "395",
         "status" : true,
         "cartogram" : 1,
         "name" : "Robertson"
      }
   },
   {
      "fields" : {
         "cartogram" : 1,
         "status" : true,
         "entity_id" : "493",
         "name" : "Wilson"
      },
      "model" : "cartograms.cartogramentity",
      "pk" : 245
   },
   {
      "fields" : {
         "cartogram" : 1,
         "status" : true,
         "entity_id" : "353",
         "name" : "Nolan"
      },
      "model" : "cartograms.cartogramentity",
      "pk" : 246
   },
   {
      "pk" : 247,
      "model" : "cartograms.cartogramentity",
      "fields" : {
         "name" : "Cottle",
         "cartogram" : 1,
         "status" : true,
         "entity_id" : "101"
      }
   },
   {
      "fields" : {
         "cartogram" : 1,
         "status" : true,
         "entity_id" : "057",
         "name" : "Calhoun"
      },
      "model" : "cartograms.cartogramentity",
      "pk" : 248
   },
   {
      "pk" : 249,
      "model" : "cartograms.cartogramentity",
      "fields" : {
         "cartogram" : 1,
         "status" : true,
         "entity_id" : "397",
         "name" : "Rockwall"
      }
   },
   {
      "pk" : 250,
      "model" : "cartograms.cartogramentity",
      "fields" : {
         "name" : "Live Oak",
         "cartogram" : 1,
         "entity_id" : "297",
         "status" : true
      }
   },
   {
      "fields" : {
         "status" : true,
         "entity_id" : "345",
         "cartogram" : 1,
         "name" : "Motley"
      },
      "pk" : 251,
      "model" : "cartograms.cartogramentity"
   },
   {
      "pk" : 252,
      "model" : "cartograms.cartogramentity",
      "fields" : {
         "name" : "Sherman",
         "entity_id" : "421",
         "status" : true,
         "cartogram" : 1
      }
   },
   {
      "model" : "cartograms.cartogramentity",
      "pk" : 253,
      "fields" : {
         "name" : "Ochiltree",
         "cartogram" : 1,
         "entity_id" : "357",
         "status" : true
      }
   },
   {
      "pk" : 254,
      "model" : "cartograms.cartogramentity",
      "fields" : {
         "name" : "Comal",
         "status" : true,
         "entity_id" : "091",
         "cartogram" : 1
      }
   }
]
